asciidoctor_backend/__init__.py
asciidoctor_backend/config.py
asciidoctor_backend/file_processor.py
asciidoctor_backend/html_processor.py
asciidoctor_backend/models.py
asciidoctor_backend/plugin.py
asciidoctor_backend/renderer.py
asciidoctor_backend/utils.py
asciidoctor_backend/assets/asciidoc.css
asciidoctor_backend/assets/include_edit.rb
asciidoctor_backend/assets/strip_callouts.js
mkdocs_asciidoctor_backend-0.1.13.dist-info/METADATA
mkdocs_asciidoctor_backend-0.1.13.dist-info/WHEEL
mkdocs_asciidoctor_backend-0.1.13.dist-info/entry_points.txt
mkdocs_asciidoctor_backend-0.1.13.dist-info/top_level.txt
mkdocs_asciidoctor_backend-0.1.13.dist-info/RECORD
