Metadata-Version: 2.4
Name: mkdocs-asciidoctor-backend
Version: 0.1.13
Summary: Asciidoctor backend for MkDocs
Author: Aidan Reilly
License: MIT
Project-URL: Homepage, https://github.com/aireilly/mkdocs-asciidoctor-backend
Project-URL: Source, https://github.com/aireilly/mkdocs-asciidoctor-backend
Project-URL: Issues, https://github.com/aireilly/mkdocs-asciidoctor-backend/issues
Keywords: mkdocs,asciidoctor,plugin
Classifier: Framework :: MkDocs
Classifier: Programming Language :: Python :: 3
Classifier: License :: OSI Approved :: MIT License
Classifier: Operating System :: OS Independent
Requires-Python: >=3.9
Requires-Dist: mkdocs>=1.6
Requires-Dist: beautifulsoup4>=4.11
Requires-Dist: lxml>=4.9
Provides-Extra: dev
Requires-Dist: pytest>=8; extra == "dev"
